setup.py
seapy/__init__.py
seapy/base.py
seapy/objects_map.py
seapy/other.py
seapy/system.py
seapy/tools.py
seapy/version.py
seapy.egg-info/PKG-INFO
seapy.egg-info/SOURCES.txt
seapy.egg-info/dependency_links.txt
seapy.egg-info/not-zip-safe
seapy.egg-info/requires.txt
seapy.egg-info/top_level.txt
seapy/components/__init__.py
seapy/components/acoustical.py
seapy/components/acoustical1d.py
seapy/components/acoustical2d.py
seapy/components/acoustical3d.py
seapy/components/beam.py
seapy/components/component.py
seapy/components/pipe.py
seapy/components/plate.py
seapy/components/structural.py
seapy/components/structural3d.py
seapy/couplings/__init__.py
seapy/couplings/coupling.py
seapy/couplings/coupling2dcavities2d.py
seapy/couplings/couplinglinestructural.py
seapy/couplings/couplingpointstructural.py
seapy/couplings/couplingsurfaceacoustical.py
seapy/couplings/couplingsurfaceacousticalplate.py
seapy/couplings/couplingsurfaceplateacoustical.py
seapy/excitations/__init__.py
seapy/excitations/excitation.py
seapy/excitations/excitationpoint.py
seapy/excitations/excitationrain.py
seapy/junctions/__init__.py
seapy/junctions/junction.py
seapy/materials/__init__.py
seapy/materials/material.py
seapy/materials/materialgas.py
seapy/materials/materialsolid.py
seapy/subsystems/__init__.py
seapy/subsystems/subsystem.py
seapy/subsystems/subsystemacoustical.py
seapy/subsystems/subsystemstructural.py