Metadata-Version: 1.0
Name: seapy
Version: 0.1.0.dev-63e51ed
Summary: Statistical Energy Analysis module for Python.
Home-page: UNKNOWN
Author: Frederik Rietdijk
Author-email: fridh@fridh.nl
License: LICENSE.txt
Platform: UNKNOWN
